uurl/__init__.py
uurl/host.py
uurl/path.py
uurl/port.py
uurl/protocol.py
uurl/url.py
uurl-0.0.2.dist-info/AUTHORS.md
uurl-0.0.2.dist-info/LICENSE.md
uurl-0.0.2.dist-info/METADATA
uurl-0.0.2.dist-info/WHEEL
uurl-0.0.2.dist-info/top_level.txt
uurl-0.0.2.dist-info/RECORD
