Metadata-Version: 2.1
Name: uurl
Version: 0.0.2
Summary: Package contains a set of interfaces to operate `uurl` application.
Home-page: https://github.com/vyahello/uurl
Author: Volodymyr Yahello
Author-email: vyahello@gmail.com
License: UNKNOWN
Platform: UNKNOWN
Classifier: Programming Language :: Python :: 3.6
Classifier: Programming Language :: Python :: 3.7
Classifier: Programming Language :: Python :: 3.8
Classifier: License :: OSI Approved :: MIT License
Classifier: Operating System :: OS Independent
Requires-Python: >=3.6
Requires-Dist: attrs (==19.3.0)
Requires-Dist: click (==7.1.1)
Requires-Dist: dataclasses (==0.6)
Requires-Dist: enforce-pep8 (==0.0.10)
Requires-Dist: pypans (==0.0.13)
Requires-Dist: requests (==2.23.0)
Requires-Dist: urequest (==0.0.6)
Requires-Dist: urllib3 (==1.25.10)
